primeiraapi/__init__.py
primeiraapi/core.py
primeiraapi_package-1.0.0.dist-info/METADATA
primeiraapi_package-1.0.0.dist-info/WHEEL
primeiraapi_package-1.0.0.dist-info/top_level.txt
primeiraapi_package-1.0.0.dist-info/RECORD
